[
  {
    "id": 1,
    "text": "azertyui lidzjq doqi jzlqidj qzjdljzo",
    "storyId": 2,
    "nbCartons": 5
  },
  {
    "id": 2,
    "text": "aaaaaaaaaaaaaaaa dlajzdljiiiiiiiiiiiii ",
    "storyId": 3
  },
  {
    "id": 3,
    "text": "jhgdfqizlghd",
    "storyId": 4,
    "nbCartons": 3
  },
  {
    "id": 4,
    "text": "aaaaaaaaaaaaaqzkdlnqzlaaa dlajzdljiiiiiiiiiiiii ",
    "storyId": 5
  },
  {
    "id": 5,
    "text": "qzdùkkldzkz, kl,d lkdqzkl,dqzkl,dqz kl,",
    "storyId": 6
  },
  {
    "id": 6,
    "text": "aaaaaaaaaaaaaaaa dlaaaaaaaaaaaajzdljiiiiiiiiiiiii ",
    "storyId": 7
  },
  {
    "id": 7,
    "text": "jjjjjjjjjjj jdjjsjdqzjkq ",
    "storyId": 8
  }
]